kgsteward/__init__.py
kgsteward/common.py
kgsteward/fileserver.py
kgsteward/fuseki.py
kgsteward/generic.py
kgsteward/graphdb.py
kgsteward/kgsteward.py
kgsteward/oxigraph.py
kgsteward/qlever.py
kgsteward/qlever2.py
kgsteward/rdf4j.py
kgsteward/special.py
kgsteward/yamlconfig.py
kgsteward-3.1.5.dist-info/METADATA
kgsteward-3.1.5.dist-info/WHEEL
kgsteward-3.1.5.dist-info/entry_points.txt
kgsteward-3.1.5.dist-info/licenses/LICENSE
kgsteward-3.1.5.dist-info/RECORD
