Metadata-Version: 2.4
Name: kgsteward
Version: 3.1.5
Summary: Knowledge Graph Steward - Command line tool to manage content of RDF store
Project-URL: Homepage, https://github.com/sib-swiss/kgsteward
Project-URL: Bug Tracker, https://github.com/sib-swiss/kgsteward/issues
Project-URL: Documentation, https://github.com/sib-swiss/kgsteward
Project-URL: Source, https://github.com/sib-swiss/kgsteward
Author-email: Marco Pagni <marco.pagni@sib.swiss>
License:                     GNU GENERAL PUBLIC LICENSE
License-File: LICENSE
Classifier: Development Status :: 4 - Beta
Classifier: License :: OSI Approved :: GNU General Public License v3 (GPLv3)
Classifier: Operating System :: OS Independent
Classifier: Programming Language :: Python :: 3
Requires-Python: >=3.9
Requires-Dist: dumper
Requires-Dist: pathlib
Requires-Dist: pprintpp>=0.4.0
Requires-Dist: pydantic>=2.10.0
Requires-Dist: pyyaml
Requires-Dist: pyyaml-include>=2.2
Requires-Dist: rdflib>=6.3.2
Requires-Dist: requests
Requires-Dist: termcolor
